[
    {
        "question": "Question Musique niveau 6",
        "reponse": ""
    },
    {
        "question": "Question Musique niveau 6",
        "reponse": ""
    },
    {
        "question": "Question Musique niveau 6",
        "reponse": ""
    },
    {
        "question": "Question Musique niveau 6",
        "reponse": ""
    },
    {
        "question": "Question Musique niveau 6",
        "reponse": ""
    },
    {
        "question": "Question Musique niveau 6",
        "reponse": ""
    },
    {
        "question": "Question Musique niveau 6",
        "reponse": ""
    },
    {
        "question": "Question Musique niveau 6",
        "reponse": ""
    },
    {
        "question": "Question Musique niveau 6",
        "reponse": ""
    },
    {
        "question": "Question Musique niveau 6",
        "reponse": ""
    }
]