[
    {
        "question": "En quelle année le ZEvent a dépassé pour la premiere fois le milion d'euros ?",
        "reponse": "2018"
    },
    {
        "question": "Dans GTA RPZ, quel est le nom de famille d'Antoine et Daniel ?",
        "reponse": "Croute"
    },
    {
        "question": "Question Twitch niveau 3",
        "reponse": ""
    },
    {
        "question": "Question Twitch niveau 3",
        "reponse": ""
    },
    {
        "question": "Question Twitch niveau 3",
        "reponse": ""
    },
    {
        "question": "Question Twitch niveau 3",
        "reponse": ""
    },
    {
        "question": "Question Twitch niveau 3",
        "reponse": ""
    },
    {
        "question": "Question Twitch niveau 3",
        "reponse": ""
    },
    {
        "question": "Question Twitch niveau 3",
        "reponse": ""
    },
    {
        "question": "Question Twitch niveau 3",
        "reponse": ""
    }
]